cartesi/__init__.py
cartesi/_eth_abi_packed.py
cartesi/abi.py
cartesi/dapp.py
cartesi/models.py
cartesi/rollup.py
cartesi/test_abi.py
cartesi/testclient.py
cartesi/vouchers.py
cartesi/router/__init__.py
cartesi/router/abi.py
cartesi/router/base.py
cartesi/router/dapp_address.py
cartesi/router/json.py
cartesi/router/multi.py
cartesi/router/url.py
cartesi/wallet/__init__.py
cartesi/wallet/ether.py
python_cartesi-0.1.1.dist-info/LICENSE
python_cartesi-0.1.1.dist-info/METADATA
python_cartesi-0.1.1.dist-info/WHEEL
python_cartesi-0.1.1.dist-info/top_level.txt
python_cartesi-0.1.1.dist-info/RECORD
