Metadata-Version: 2.1
Name: python-cartesi
Version: 0.1.1
Summary: A Python Framework for Cartesi Distributed Applications
Author-email: Felipe Fink Grael <felipefg@prototyp3.dev>
Project-URL: Homepage, https://github.com/prototyp3-dev/python-cartesi
Classifier: Programming Language :: Python :: 3
Classifier: License :: OSI Approved :: Apache Software License
Classifier: Operating System :: OS Independent
Requires-Python: >=3.10
License-File: LICENSE
Requires-Dist: requests >=2.31.0
Requires-Dist: pydantic <2
Requires-Dist: pytest ~=7.4.0
Requires-Dist: eth-abi ~=4.2.1
Requires-Dist: pycryptodome ~=3.19.0
